odoo/addons/purchase_stock_vendor_bill_breakdown/README.rst
odoo/addons/purchase_stock_vendor_bill_breakdown/__init__.py
odoo/addons/purchase_stock_vendor_bill_breakdown/__manifest__.py
odoo/addons/purchase_stock_vendor_bill_breakdown/i18n/es.po
odoo/addons/purchase_stock_vendor_bill_breakdown/i18n/it.po
odoo/addons/purchase_stock_vendor_bill_breakdown/i18n/purchase_stock_vendor_bill_breakdown.pot
odoo/addons/purchase_stock_vendor_bill_breakdown/models/__init__.py
odoo/addons/purchase_stock_vendor_bill_breakdown/models/purchase_order_line.py
odoo/addons/purchase_stock_vendor_bill_breakdown/readme/CONTRIBUTORS.rst
odoo/addons/purchase_stock_vendor_bill_breakdown/readme/DESCRIPTION.rst
odoo/addons/purchase_stock_vendor_bill_breakdown/static/description/icon.png
odoo/addons/purchase_stock_vendor_bill_breakdown/static/description/index.html
odoo/addons/purchase_stock_vendor_bill_breakdown/tests/__init__.py
odoo/addons/purchase_stock_vendor_bill_breakdown/tests/test_stock_purchase_order_line.py
odoo14_addon_purchase_stock_vendor_bill_breakdown-14.0.1.0.1.dev10.dist-info/METADATA
odoo14_addon_purchase_stock_vendor_bill_breakdown-14.0.1.0.1.dev10.dist-info/WHEEL
odoo14_addon_purchase_stock_vendor_bill_breakdown-14.0.1.0.1.dev10.dist-info/top_level.txt
odoo14_addon_purchase_stock_vendor_bill_breakdown-14.0.1.0.1.dev10.dist-info/RECORD
